redbaby/__init__.py
redbaby/database.py
redbaby/document.py
redbaby/errors.py
redbaby/hashing.py
redbaby/pyobjectid.py
redbaby/utils.py
redbaby/behaviors/__init__.py
redbaby/behaviors/areading.pyi
redbaby/behaviors/core.py
redbaby/behaviors/hashids.py
redbaby/behaviors/objectids.py
redbaby/behaviors/reading.py
redbaby/behaviors/softdeletion.py
redbaby/behaviors/timestamping.py
redbaby-1.0.5.dist-info/LICENSE
redbaby-1.0.5.dist-info/METADATA
redbaby-1.0.5.dist-info/WHEEL
redbaby-1.0.5.dist-info/top_level.txt
redbaby-1.0.5.dist-info/RECORD
