Metadata-Version: 2.1
Name: redbaby
Version: 1.0.5
Summary: Mini reimplementation of REDB, baby redb, redbaby.
Home-page: https://github.com/teialabs/redbaby
Author: Nei Cardoso de Oliveira Neto
Author-email: nei@teialabs.com
Requires-Python: >=3.11
License-File: LICENSE
Requires-Dist: compose
Requires-Dist: compose-stubs
Requires-Dist: crypteia ==1.0.1
Requires-Dist: pydantic
Requires-Dist: pydantic-settings
Requires-Dist: pymongo
